{
  "project": "quotex-hft-bot",
  "description": "Bot de opciones binarias en Quotex. Estrategias vivas: consolidación (STRAT-A), momentum 1m, reversal swing, order block. NUEVA: STRAT-F (Fractal/Wyckoff, marco M15/M5/M1). Gestión Massaniello.",
  "note": "Strategy B (Wyckoff Spring/Sweep) fue ELIMINADA físicamente el 2026-07-11. Este roadmap reemplaza al anterior (feature_list.json viejo + docs/ROADMAP*.md borrados).",
  "roadmap": {
    "version": "2026-07-11",
    "strategy_focus": "strat_f",
    "next_recommended": "none (STRAT-F + dashboard cerrados)"
  },
  "rules": {
    "one_feature_at_a_time": true,
    "require_tests_to_close": true
  },
  "features": [
    {
      "id": 1,
      "name": "scanner_multi_tf_prefetch",
      "title": "Prefetch de 15m en el ciclo del scanner",
      "phase": "scanner_accommodation",
      "priority": 1,
      "description": "Hacer que scan_prefetch traiga velas de 15m además de 5m/1m y exponerlas en ScanCycleData.candles_15m, para que STRAT-F tenga contexto M15 sin I/O en el hot path.",
      "acceptance": [
        "ScanCycleData expone candles_15m: dict[str, list[Candle]]",
        "prefetch_primary_candles baja TF_15M junto a TF_5M/TF_1M",
        "El scan sigue sin I/O bloqueante por activo en la fase de evaluación",
        "tests cubren que candles_15m llega poblado para los activos del ciclo",
        "pytest tests/ en verde"
      ],
      "status": "done"
    },
    {
      "id": 2,
      "name": "strat_f_baseline",
      "title": "STRAT-F: evaluador puro (fractal M5 + contexto M15 + rechazo M1)",
      "phase": "strat_f",
      "priority": 2,
      "description": "Crear src/strat_fractal.py con evaluate_strat_f(candles_15m, candles_5m, candles_1m, payout) -> StratFEvaluation (sin I/O). Detecta fractal Bill Williams de 5 velas en M5 dentro de una banda/zona, valida que M15 esté en rango (no roto) y que M1 rechace la banda. Devuelve direction CALL/PUT, zona, strength, confirms.",
      "acceptance": [
        "Existe src/strat_fractal.py con evaluate_strat_f()",
        "Detecta fractal arriba/abajo de 5 velas en M5",
        "Usa M15 para contexto (rango vs tendencia rota) y lo aplica como filtro",
        "Usa M1 para confirmar rechazo (vela toca banda y no cierra fuera)",
        "Devuelve StratFEvaluation con has_signal/direction/zone/strength/confirms",
        "tests/test_strat_fractal.py >= 8 casos (fractal up/down, M15 roto, sin rechazo M1, etc.)",
        "pytest en verde"
      ],
      "status": "done",
      "depends_on": [
        1
      ]
    },
    {
      "id": 3,
      "name": "strat_f_scanner_wiring",
      "title": "Cablear STRAT-F en el scanner",
      "phase": "strat_f",
      "priority": 3,
      "description": "En _scan_phase_evaluate_assets, añadir bloque STRAT-F que llame evaluate_strat_f con candles_15m/5m/1m y cree CandidateEntry con _strategy_origin='STRAT-F', _signal_ts_1m y stats strat_f_signals. Respetar STRAT_A_ONLY y STRAT_F_ENABLED.",
      "acceptance": [
        "scanner.py importa evaluate_strat_f y lo invoca en el ciclo",
        "CandidateEntry de STRAT-F lleva _strategy_origin='STRAT-F'",
        "stats['strat_f_signals'] se incrementa y se loguea [STRAT-F]",
        "Bajo STRAT_A_ONLY no se evalua STRAT-F",
        "tests/test_scanner_strat_f.py cubre el cableado (mock candles)",
        "pytest en verde"
      ],
      "status": "done",
      "depends_on": [
        2
      ]
    },
    {
      "id": 4,
      "name": "strat_f_filters",
      "title": "STRAT-F: filtros de calidad (alineación + payout + edad)",
      "phase": "strat_f",
      "priority": 4,
      "description": "Endurecer STRAT-F: payout >= STRAT_F_MIN_PAYOUT, alineacion M15/M5 obligatoria, edad minima de la zona/banda, y reject-first con log explicito cuando falta alineacion.",
      "acceptance": [
        "Config: STRAT_F_MIN_PAYOUT, STRAT_F_MIN_SCORE, STRAT_F_ZONE_MIN_AGE",
        "Sin alineacion M15/M5 -> rechazo con razon logueada",
        "Payout < minimo -> activo excluido del scan STRAT-F",
        "tests verifican cada veto por separado",
        "pytest en verde"
      ],
      "status": "done",
      "depends_on": [
        3
      ]
    },
    {
      "id": 5,
      "name": "strat_f_backtest",
      "title": "STRAT-F: reconocimiento en backtester",
      "phase": "validation",
      "priority": 5,
      "description": "Hacer que src/backtester.py reconozca origen 'STRAT-F' y simule sus señales sobre datos historicos.",
      "acceptance": [
        "Backtester admite 'STRAT-F' en STRATEGY_MAP / rama de origen",
        "Reporte diferencia win rate y profit de STRAT-F vs otras",
        "pytest en verde"
      ],
      "status": "done",
      "depends_on": [
        3
      ]
    },
    {
      "id": 6,
      "name": "strat_f_live_validation",
      "title": "STRAT-F: validación demo en vivo",
      "phase": "validation",
      "priority": 6,
      "description": "Validar STRAT-F en PRACTICE con Massaniello: sesion 60min, meta 5 entradas / 3 ITM o evidencia de reject-first correcto.",
      "acceptance": [
        "Bot ejecutado solo STRAT-F (otras off) >=60 min en PRACTICE",
        "Log documenta señales, rechazos y entradas STRAT-F",
        "Resumen en progress/history.md"
      ],
      "status": "done",
      "depends_on": [
        4,
        5
      ]
    },
    {
      "id": 7,
      "title": "Reemplazo del dashboard por panel STRAT-F (aceptadas vs rechazadas con razón)",
      "spec": "hub_strat_f_replacement",
      "status": "done",
      "sdd": true,
      "depends_on": [
        1,
        2,
        3,
        4,
        5,
        6
      ],
      "name": "hub_strat_f_replacement"
    },
    {
      "id": 8,
      "name": "schedule_auto",
      "title": "Schedule auto full (Consola)",
      "phase": "hub_ops",
      "priority": 8,
      "description": "Modo manual/auto_full: expiracion en min, sesiones seguidas, horas trabajo/descanso, max sesiones/dia; persist data/hub_schedule.json; ScheduleController.",
      "acceptance": [
        "UI Consola sin monto base / max loss / concurrent / daily / STRAT-F Only",
        "duration_min -> duration_sec en servidor",
        "hub_schedule.json load/save",
        "auto_full: work block stop + rest + auto resume",
        "tests verdes"
      ],
      "status": "in_progress",
      "sdd": true,
      "spec_path": "specs/schedule_auto/"
    }
  ]
}
